{
  "ekadashi_list": [
    {
      "name": "রমা একাদশী",
      "date": "2025-11-15",
      "paran_start": "06:40",
      "paran_end": "09:10",
      "verified": "ISKCON"
    },
    {
      "name": "উৎপন্না একাদশী",
      "date": "2025-11-30",
      "paran_start": "06:42",
      "paran_end": "09:08",
      "verified": "ISKCON"
    },
    {
      "name": "মোক্ষদা একাদশী",
      "date": "2025-12-14",
      "paran_start": "06:30",
      "paran_end": "08:55"
    },
    {
      "name": "সাফল্যা একাদশী",
      "date": "2026-01-10",
      "paran_start": "06:45",
      "paran_end": "09:15"
    },
    {
      "name": "পুত্রদা একাদশী",
      "date": "2026-01-29"
    },
    {
      "name": "ষটতিলা একাদশী",
      "date": "2026-02-09"
    },
    {
      "name": "বিজয়া একাদশী",
      "date": "2026-02-25"
    },
    {
      "name": "আমলকি একাদশী",
      "date": "2026-03-11"
    },
    {
      "name": "পাপমোচনী একাদশী",
      "date": "2026-03-27"
    },
    {
      "name": "কমলা একাদশী",
      "date": "2026-04-10"
    },
    {
      "name": "বরুথিনী একাদশী",
      "date": "2026-04-24"
    },
    {
      "name": "মোহিনী একাদশী",
      "date": "2026-05-09"
    },
    {
      "name": "আপরা একাদশী",
      "date": "2026-05-24"
    },
    {
      "name": "পান্ডব নির্জলা একাদশী",
      "date": "2026-06-08"
    },
    {
      "name": "যোগিনী একাদশী",
      "date": "2026-06-23"
    },
    {
      "name": "শায়নী একাদশী",
      "date": "2026-07-08"
    },
    {
      "name": "কামিকা একাদশী",
      "date": "2026-07-23"
    },
    {
      "name": "পবিত্রা একাদশী",
      "date": "2026-08-07"
    },
    {
      "name": "অন্নদা একাদশী",
      "date": "2026-08-22"
    },
    {
      "name": "পরশুরাম একাদশী",
      "date": "2026-09-06"
    },
    {
      "name": "ইন্দিরা একাদশী",
      "date": "2026-09-20"
    },
    {
      "name": "পাশাঙ্কুষা একাদশী",
      "date": "2026-10-06"
    },
    {
      "name": "রমা একাদশী",
      "date": "2026-10-21"
    },
    {
      "name": "উৎপন্না একাদশী",
      "date": "2026-11-05"
    }
  ]
}
